{
	"info": {
		"_postman_id": "504e7e19-d06d-4a12-809a-f744f0445fe6",
		"name": "Blog",
		"description": "This is a simple blogging service provide `Rest API` for consumer to build their application on demand.",
		"schema": "https://schema.getpostman.com/json/collection/v2.1.0/collection.json"
	},
	"item": [
		{
			"name": "Users",
			"item": [
				{
					"name": "V2",
					"item": [
						{
							"name": "Create user",
							"request": {
								"auth": {
									"type": "basic",
									"basic": [
										{
											"key": "password",
											"value": "password",
											"type": "string"
										},
										{
											"key": "username",
											"value": "username",
											"type": "string"
										},
										{
											"key": "saveHelperData",
											"type": "any"
										},
										{
											"key": "showPassword",
											"value": false,
											"type": "boolean"
										}
									]
								},
								"method": "POST",
								"header": [],
								"body": {
									"mode": "urlencoded",
									"urlencoded": [
										{
											"key": "name",
											"value": "Tom Hanks",
											"type": "text"
										},
										{
											"key": "bio",
											"value": "Thomas Jeffrey Hanks is an American actor and filmmaker. Known for both his comedic and dramatic roles, Hanks is one of the most popular and recognizable film stars worldwide, and is widely regarded as an American cultural icon.",
											"type": "text"
										}
									],
									"options": {
										"raw": {
											"language": "json"
										}
									}
								},
								"url": {
									"raw": "{{blog-server}}/v2/users",
									"host": [
										"{{blog-server}}"
									],
									"path": [
										"v2",
										"users"
									]
								},
								"description": "Create user use `JSON` payload to create a user"
							},
							"response": [
								{
									"name": "Validation Error",
									"originalRequest": {
										"method": "POST",
										"header": [],
										"body": {
											"mode": "urlencoded",
											"urlencoded": [
												{
													"key": "name",
													"value": "",
													"type": "text"
												},
												{
													"key": "bio",
													"value": "",
													"type": "text"
												}
											],
											"options": {
												"raw": {
													"language": "json"
												}
											}
										},
										"url": {
											"raw": "{{blog-server}}/v2/users",
											"host": [
												"{{blog-server}}"
											],
											"path": [
												"v2",
												"users"
											]
										}
									},
									"status": "Unprocessable Entity",
									"code": 422,
									"_postman_previewlanguage": "json",
									"header": [
										{
											"key": "Content-Type",
											"value": "application/json; charset=utf-8"
										},
										{
											"key": "Date",
											"value": "Sun, 10 May 2020 18:26:56 GMT"
										},
										{
											"key": "Content-Length",
											"value": "105"
										}
									],
									"cookie": [],
									"body": "{\n    \"errors\": {\n        \"bio\": [\n            \"Bio can not be empty\"\n        ],\n        \"name\": [\n            \"Name can not be empty\"\n        ]\n    },\n    \"message\": \"Validation error\"\n}"
								},
								{
									"name": "Success",
									"originalRequest": {
										"method": "POST",
										"header": [],
										"body": {
											"mode": "urlencoded",
											"urlencoded": [
												{
													"key": "name",
													"value": "Tom Hanks",
													"type": "text"
												},
												{
													"key": "bio",
													"value": "Thomas Jeffrey Hanks is an American actor and filmmaker. Known for both his comedic and dramatic roles, Hanks is one of the most popular and recognizable film stars worldwide, and is widely regarded as an American cultural icon.",
													"type": "text"
												}
											],
											"options": {
												"raw": {
													"language": "json"
												}
											}
										},
										"url": {
											"raw": "{{blog-server}}/v2/users",
											"host": [
												"{{blog-server}}"
											],
											"path": [
												"v2",
												"users"
											]
										}
									},
									"status": "Created",
									"code": 201,
									"_postman_previewlanguage": "json",
									"header": [
										{
											"key": "Content-Type",
											"value": "application/json; charset=utf-8"
										},
										{
											"key": "Date",
											"value": "Sun, 10 May 2020 18:27:21 GMT"
										},
										{
											"key": "Content-Length",
											"value": "311"
										}
									],
									"cookie": [],
									"body": "{\n    \"data\": {\n        \"id\": 1,\n        \"name\": \"Tom Hanks\",\n        \"bio\": \"Thomas Jeffrey Hanks is an American actor and filmmaker. Known for both his comedic and dramatic roles, Hanks is one of the most popular and recognizable film stars worldwide, and is widely regarded as an American cultural icon.\"\n    },\n    \"message\": \"User created successfully\"\n}"
								},
								{
									"name": "Invalid username/password",
									"originalRequest": {
										"method": "POST",
										"header": [],
										"url": {
											"raw": "{{blog-server}}/users",
											"host": [
												"{{blog-server}}"
											],
											"path": [
												"users"
											]
										}
									},
									"status": "Unauthorized",
									"code": 401,
									"_postman_previewlanguage": "json",
									"header": [
										{
											"key": "Content-Type",
											"value": "application/json; charset=utf-8"
										},
										{
											"key": "Date",
											"value": "Sun, 10 May 2020 17:46:00 GMT"
										},
										{
											"key": "Content-Length",
											"value": "34"
										}
									],
									"cookie": [],
									"body": "{\n    \"message\": \"Unauthorized attempt\"\n}"
								}
							]
						},
						{
							"name": "Update user",
							"request": {
								"auth": {
									"type": "basic",
									"basic": [
										{
											"key": "password",
											"value": "password",
											"type": "string"
										},
										{
											"key": "username",
											"value": "username",
											"type": "string"
										},
										{
											"key": "saveHelperData",
											"type": "any"
										},
										{
											"key": "showPassword",
											"value": false,
											"type": "boolean"
										}
									]
								},
								"method": "PATCH",
								"header": [],
								"body": {
									"mode": "urlencoded",
									"urlencoded": [
										{
											"key": "name",
											"value": "Mr. Tom Hanks",
											"type": "text"
										}
									],
									"options": {
										"raw": {
											"language": "json"
										}
									}
								},
								"url": {
									"raw": "{{blog-server}}/v2/users/1",
									"host": [
										"{{blog-server}}"
									],
									"path": [
										"v2",
										"users",
										"1"
									]
								},
								"description": "Create user use `JSON` payload to create a user"
							},
							"response": [
								{
									"name": "Invalid username/password",
									"originalRequest": {
										"method": "POST",
										"header": [],
										"url": {
											"raw": "{{blog-server}}/users",
											"host": [
												"{{blog-server}}"
											],
											"path": [
												"users"
											]
										}
									},
									"status": "Unauthorized",
									"code": 401,
									"_postman_previewlanguage": "json",
									"header": [
										{
											"key": "Content-Type",
											"value": "application/json; charset=utf-8"
										},
										{
											"key": "Date",
											"value": "Sun, 10 May 2020 17:46:00 GMT"
										},
										{
											"key": "Content-Length",
											"value": "34"
										}
									],
									"cookie": [],
									"body": "{\n    \"message\": \"Unauthorized attempt\"\n}"
								},
								{
									"name": "Success",
									"originalRequest": {
										"method": "PATCH",
										"header": [],
										"body": {
											"mode": "urlencoded",
											"urlencoded": [
												{
													"key": "name",
													"value": "Mr. Tom Hanks",
													"type": "text"
												}
											],
											"options": {
												"raw": {
													"language": "json"
												}
											}
										},
										"url": {
											"raw": "{{blog-server}}/v2/users/1",
											"host": [
												"{{blog-server}}"
											],
											"path": [
												"v2",
												"users",
												"1"
											]
										}
									},
									"status": "Partial Content",
									"code": 206,
									"_postman_previewlanguage": "json",
									"header": [
										{
											"key": "Content-Type",
											"value": "application/json; charset=utf-8"
										},
										{
											"key": "Date",
											"value": "Sun, 10 May 2020 18:45:04 GMT"
										},
										{
											"key": "Content-Length",
											"value": "320"
										}
									],
									"cookie": [],
									"body": "{\n    \"data\": {\n        \"id\": 1,\n        \"name\": \"Mr. Tom Hanks\",\n        \"bio\": \"Thomas Jeffrey Hanks is an American actor and filmmaker. Known for both his comedic and dramatic roles, Hanks is one of the most popular and recognizable film stars worldwide, and is widely regarded as an American cultural icon.\"\n    },\n    \"message\": \"User partial update successful\"\n}"
								}
							]
						}
					],
					"description": "`V2` contains all the version *2.0* endpoints for users",
					"protocolProfileBehavior": {},
					"_postman_isSubFolder": true
				},
				{
					"name": "Create user",
					"request": {
						"auth": {
							"type": "basic",
							"basic": [
								{
									"key": "password",
									"value": "password",
									"type": "string"
								},
								{
									"key": "username",
									"value": "username",
									"type": "string"
								},
								{
									"key": "saveHelperData",
									"type": "any"
								},
								{
									"key": "showPassword",
									"value": false,
									"type": "boolean"
								}
							]
						},
						"method": "POST",
						"header": [],
						"body": {
							"mode": "raw",
							"raw": "{\n\t\"name\": \"Captain Jack Sparrow\",\n\t\"bio\": \"Captain Jack Sparrow is a fictional character and the main protagonist of the Pirates of the Caribbean film series. The character was created by screenwriters Ted Elliott and Terry Rossio and is portrayed by Johnny Depp\"\n}",
							"options": {
								"raw": {
									"language": "json"
								}
							}
						},
						"url": {
							"raw": "{{blog-server}}/v1/users",
							"host": [
								"{{blog-server}}"
							],
							"path": [
								"v1",
								"users"
							]
						},
						"description": "Create user use `JSON` payload to create a user"
					},
					"response": [
						{
							"name": "Invalid username/password",
							"originalRequest": {
								"method": "POST",
								"header": [],
								"url": {
									"raw": "{{blog-server}}/users",
									"host": [
										"{{blog-server}}"
									],
									"path": [
										"users"
									]
								}
							},
							"status": "Unauthorized",
							"code": 401,
							"_postman_previewlanguage": "json",
							"header": [
								{
									"key": "Content-Type",
									"value": "application/json; charset=utf-8"
								},
								{
									"key": "Date",
									"value": "Sun, 10 May 2020 17:46:00 GMT"
								},
								{
									"key": "Content-Length",
									"value": "34"
								}
							],
							"cookie": [],
							"body": "{\n    \"message\": \"Unauthorized attempt\"\n}"
						},
						{
							"name": "Empty body",
							"originalRequest": {
								"method": "POST",
								"header": [],
								"body": {
									"mode": "raw",
									"raw": "",
									"options": {
										"raw": {
											"language": "json"
										}
									}
								},
								"url": {
									"raw": "{{blog-server}}/users",
									"host": [
										"{{blog-server}}"
									],
									"path": [
										"users"
									]
								}
							},
							"status": "Bad Request",
							"code": 400,
							"_postman_previewlanguage": "json",
							"header": [
								{
									"key": "Content-Type",
									"value": "application/json; charset=utf-8"
								},
								{
									"key": "Date",
									"value": "Sun, 10 May 2020 17:46:49 GMT"
								},
								{
									"key": "Content-Length",
									"value": "34"
								}
							],
							"cookie": [],
							"body": "{\n    \"message\": \"Invalid request body\"\n}"
						},
						{
							"name": "Validation error",
							"originalRequest": {
								"method": "POST",
								"header": [],
								"body": {
									"mode": "raw",
									"raw": "{\n\t\"name\": \"\",\n\t\"bio\": \"\"\n}",
									"options": {
										"raw": {
											"language": "json"
										}
									}
								},
								"url": {
									"raw": "{{blog-server}}/users",
									"host": [
										"{{blog-server}}"
									],
									"path": [
										"users"
									]
								}
							},
							"status": "Unprocessable Entity",
							"code": 422,
							"_postman_previewlanguage": "json",
							"header": [
								{
									"key": "Content-Type",
									"value": "application/json; charset=utf-8"
								},
								{
									"key": "Date",
									"value": "Sun, 10 May 2020 17:52:37 GMT"
								},
								{
									"key": "Content-Length",
									"value": "105"
								}
							],
							"cookie": [],
							"body": "{\n    \"errors\": {\n        \"bio\": [\n            \"Bio can not be empty\"\n        ],\n        \"name\": [\n            \"Name can not be empty\"\n        ]\n    },\n    \"message\": \"Validation error\"\n}"
						},
						{
							"name": "Success",
							"originalRequest": {
								"method": "POST",
								"header": [],
								"body": {
									"mode": "raw",
									"raw": "{\n\t\"name\": \"Tom Hanks\",\n\t\"bio\": \"Thomas Jeffrey Hanks is an American actor and filmmaker. Known for both his comedic and dramatic roles, Hanks is one of the most popular and recognizable film stars worldwide, and is widely regarded as an American cultural icon.\"\n}",
									"options": {
										"raw": {
											"language": "json"
										}
									}
								},
								"url": {
									"raw": "{{blog-server}}/users",
									"host": [
										"{{blog-server}}"
									],
									"path": [
										"users"
									]
								}
							},
							"status": "Created",
							"code": 201,
							"_postman_previewlanguage": "json",
							"header": [
								{
									"key": "Content-Type",
									"value": "application/json; charset=utf-8"
								},
								{
									"key": "Date",
									"value": "Sun, 10 May 2020 17:53:27 GMT"
								},
								{
									"key": "Content-Length",
									"value": "311"
								}
							],
							"cookie": [],
							"body": "{\n    \"data\": {\n        \"id\": 1,\n        \"name\": \"Tom Hanks\",\n        \"bio\": \"Thomas Jeffrey Hanks is an American actor and filmmaker. Known for both his comedic and dramatic roles, Hanks is one of the most popular and recognizable film stars worldwide, and is widely regarded as an American cultural icon.\"\n    },\n    \"message\": \"User created successfully\"\n}"
						}
					]
				},
				{
					"name": "Fetch user",
					"request": {
						"auth": {
							"type": "basic",
							"basic": [
								{
									"key": "password",
									"value": "password",
									"type": "string"
								},
								{
									"key": "username",
									"value": "username",
									"type": "string"
								},
								{
									"key": "saveHelperData",
									"type": "any"
								},
								{
									"key": "showPassword",
									"value": false,
									"type": "boolean"
								}
							]
						},
						"method": "GET",
						"header": [],
						"url": {
							"raw": "{{blog-server}}/v1/users/{{id}}",
							"host": [
								"{{blog-server}}"
							],
							"path": [
								"v1",
								"users",
								"{{id}}"
							]
						},
						"description": "Fetch a single user using `id`"
					},
					"response": [
						{
							"name": "Success",
							"originalRequest": {
								"method": "GET",
								"header": [],
								"url": {
									"raw": "{{blog-server}}/v1/users/{{id}}",
									"host": [
										"{{blog-server}}"
									],
									"path": [
										"v1",
										"users",
										"{{id}}"
									]
								}
							},
							"status": "OK",
							"code": 200,
							"_postman_previewlanguage": "json",
							"header": [
								{
									"key": "Content-Type",
									"value": "application/json; charset=utf-8"
								},
								{
									"key": "Date",
									"value": "Sun, 10 May 2020 18:49:32 GMT"
								},
								{
									"key": "Content-Length",
									"value": "273"
								}
							],
							"cookie": [],
							"body": "{\n    \"data\": {\n        \"id\": 1,\n        \"name\": \"Tom Hanks\",\n        \"bio\": \"Thomas Jeffrey Hanks is an American actor and filmmaker. Known for both his comedic and dramatic roles, Hanks is one of the most popular and recognizable film stars worldwide, and is widely regarded as an American cultural icon.\"\n    }\n}"
						},
						{
							"name": "Invalid user id",
							"originalRequest": {
								"method": "GET",
								"header": [],
								"url": {
									"raw": "{{blog-server}}/v1/users/{{invalid-id}}",
									"host": [
										"{{blog-server}}"
									],
									"path": [
										"v1",
										"users",
										"{{invalid-id}}"
									]
								}
							},
							"status": "Bad Request",
							"code": 400,
							"_postman_previewlanguage": "json",
							"header": [
								{
									"key": "Content-Type",
									"value": "application/json; charset=utf-8"
								},
								{
									"key": "Date",
									"value": "Sun, 10 May 2020 18:49:16 GMT"
								},
								{
									"key": "Content-Length",
									"value": "29"
								}
							],
							"cookie": [],
							"body": "{\n    \"message\": \"Invalid user id\"\n}"
						},
						{
							"name": "Invalid username/password",
							"originalRequest": {
								"method": "POST",
								"header": [],
								"url": {
									"raw": "{{blog-server}}/users",
									"host": [
										"{{blog-server}}"
									],
									"path": [
										"users"
									]
								}
							},
							"status": "Unauthorized",
							"code": 401,
							"_postman_previewlanguage": "json",
							"header": [
								{
									"key": "Content-Type",
									"value": "application/json; charset=utf-8"
								},
								{
									"key": "Date",
									"value": "Sun, 10 May 2020 17:46:00 GMT"
								},
								{
									"key": "Content-Length",
									"value": "34"
								}
							],
							"cookie": [],
							"body": "{\n    \"message\": \"Unauthorized attempt\"\n}"
						}
					]
				},
				{
					"name": "Fetch users",
					"request": {
						"auth": {
							"type": "basic",
							"basic": [
								{
									"key": "password",
									"value": "password",
									"type": "string"
								},
								{
									"key": "username",
									"value": "username",
									"type": "string"
								},
								{
									"key": "saveHelperData",
									"type": "any"
								},
								{
									"key": "showPassword",
									"value": false,
									"type": "boolean"
								}
							]
						},
						"method": "GET",
						"header": [],
						"url": {
							"raw": "{{blog-server}}/v1/users?page=1&limit=20",
							"host": [
								"{{blog-server}}"
							],
							"path": [
								"v1",
								"users"
							],
							"query": [
								{
									"key": "page",
									"value": "1"
								},
								{
									"key": "limit",
									"value": "20"
								}
							]
						},
						"description": "Fetch list of users using `pagination`"
					},
					"response": [
						{
							"name": "Success",
							"originalRequest": {
								"method": "GET",
								"header": [],
								"url": {
									"raw": "{{blog-server}}/v1/users?page=1&limit=20",
									"host": [
										"{{blog-server}}"
									],
									"path": [
										"v1",
										"users"
									],
									"query": [
										{
											"key": "page",
											"value": "1",
											"description": "Page numer is a `integer` which represents the page your are requesting"
										},
										{
											"key": "limit",
											"value": "20",
											"description": "Limit it the maximum number of users listing in the result."
										}
									]
								}
							},
							"status": "OK",
							"code": 200,
							"_postman_previewlanguage": "json",
							"header": [
								{
									"key": "Content-Type",
									"value": "application/json; charset=utf-8"
								},
								{
									"key": "Date",
									"value": "Sun, 10 May 2020 18:51:18 GMT"
								},
								{
									"key": "Content-Length",
									"value": "542"
								}
							],
							"cookie": [],
							"body": "{\n    \"data\": [\n        {\n            \"id\": 1,\n            \"name\": \"Tom Hanks\",\n            \"bio\": \"Thomas Jeffrey Hanks is an American actor and filmmaker. Known for both his comedic and dramatic roles, Hanks is one of the most popular and recognizable film stars worldwide, and is widely regarded as an American cultural icon.\"\n        },\n        {\n            \"id\": 2,\n            \"name\": \"Captain Jack Sparrow\",\n            \"bio\": \"Captain Jack Sparrow is a fictional character and the main protagonist of the Pirates of the Caribbean film series. The character was created by screenwriters Ted Elliott and Terry Rossio and is portrayed by Johnny Depp\"\n        }\n    ]\n}"
						},
						{
							"name": "Invalid user id",
							"originalRequest": {
								"method": "GET",
								"header": [],
								"url": {
									"raw": "{{blog-server}}/v1/users/{{invalid-id}}",
									"host": [
										"{{blog-server}}"
									],
									"path": [
										"v1",
										"users",
										"{{invalid-id}}"
									]
								}
							},
							"status": "Bad Request",
							"code": 400,
							"_postman_previewlanguage": "json",
							"header": [
								{
									"key": "Content-Type",
									"value": "application/json; charset=utf-8"
								},
								{
									"key": "Date",
									"value": "Sun, 10 May 2020 18:49:16 GMT"
								},
								{
									"key": "Content-Length",
									"value": "29"
								}
							],
							"cookie": [],
							"body": "{\n    \"message\": \"Invalid user id\"\n}"
						},
						{
							"name": "Invalid username/password",
							"originalRequest": {
								"method": "POST",
								"header": [],
								"url": {
									"raw": "{{blog-server}}/users",
									"host": [
										"{{blog-server}}"
									],
									"path": [
										"users"
									]
								}
							},
							"status": "Unauthorized",
							"code": 401,
							"_postman_previewlanguage": "json",
							"header": [
								{
									"key": "Content-Type",
									"value": "application/json; charset=utf-8"
								},
								{
									"key": "Date",
									"value": "Sun, 10 May 2020 17:46:00 GMT"
								},
								{
									"key": "Content-Length",
									"value": "34"
								}
							],
							"cookie": [],
							"body": "{\n    \"message\": \"Unauthorized attempt\"\n}"
						}
					]
				},
				{
					"name": "Update user",
					"request": {
						"auth": {
							"type": "basic",
							"basic": [
								{
									"key": "password",
									"value": "password",
									"type": "string"
								},
								{
									"key": "username",
									"value": "username",
									"type": "string"
								},
								{
									"key": "saveHelperData",
									"type": "any"
								},
								{
									"key": "showPassword",
									"value": false,
									"type": "boolean"
								}
							]
						},
						"method": "PUT",
						"header": [],
						"body": {
							"mode": "raw",
							"raw": "{\n\t\"name\": \"Captain Jack Sparrow\",\n\t\"bio\": \"Captain Jack Sparrow is a fictional character and the main protagonist of the Pirates of the Caribbean film series. The character was created by screenwriters Ted Elliott and Terry Rossio and is portrayed by Johnny Depp\"\n}",
							"options": {
								"raw": {
									"language": "json"
								}
							}
						},
						"url": {
							"raw": "{{blog-server}}/v1/users/{{id}}",
							"host": [
								"{{blog-server}}"
							],
							"path": [
								"v1",
								"users",
								"{{id}}"
							]
						},
						"description": "Update user use `JSON` payload to create a user"
					},
					"response": [
						{
							"name": "Success",
							"originalRequest": {
								"method": "PUT",
								"header": [],
								"body": {
									"mode": "raw",
									"raw": "{\n\t\"name\": \"Captain Jack Sparrow\",\n\t\"bio\": \"Captain Jack Sparrow is a fictional character and the main protagonist of the Pirates of the Caribbean film series. The character was created by screenwriters Ted Elliott and Terry Rossio and is portrayed by Johnny Depp\"\n}",
									"options": {
										"raw": {
											"language": "json"
										}
									}
								},
								"url": {
									"raw": "{{blog-server}}/v1/users/{{id}}",
									"host": [
										"{{blog-server}}"
									],
									"path": [
										"v1",
										"users",
										"{{id}}"
									]
								}
							},
							"status": "OK",
							"code": 200,
							"_postman_previewlanguage": "json",
							"header": [
								{
									"key": "Content-Type",
									"value": "application/json; charset=utf-8"
								},
								{
									"key": "Date",
									"value": "Sun, 10 May 2020 18:56:12 GMT"
								},
								{
									"key": "Content-Length",
									"value": "313"
								}
							],
							"cookie": [],
							"body": "{\n    \"data\": {\n        \"id\": 1,\n        \"name\": \"Captain Jack Sparrow\",\n        \"bio\": \"Captain Jack Sparrow is a fictional character and the main protagonist of the Pirates of the Caribbean film series. The character was created by screenwriters Ted Elliott and Terry Rossio and is portrayed by Johnny Depp\"\n    },\n    \"message\": \"User updated successfully\"\n}"
						},
						{
							"name": "Validation error",
							"originalRequest": {
								"method": "PUT",
								"header": [],
								"body": {
									"mode": "raw",
									"raw": "{\n\t\"name\": \"\",\n\t\"bio\": \"\"\n}",
									"options": {
										"raw": {
											"language": "json"
										}
									}
								},
								"url": {
									"raw": "{{blog-server}}/v1/users/{{id}}",
									"host": [
										"{{blog-server}}"
									],
									"path": [
										"v1",
										"users",
										"{{id}}"
									]
								}
							},
							"status": "Unprocessable Entity",
							"code": 422,
							"_postman_previewlanguage": "json",
							"header": [
								{
									"key": "Content-Type",
									"value": "application/json; charset=utf-8"
								},
								{
									"key": "Date",
									"value": "Sun, 10 May 2020 18:55:56 GMT"
								},
								{
									"key": "Content-Length",
									"value": "105"
								}
							],
							"cookie": [],
							"body": "{\n    \"errors\": {\n        \"bio\": [\n            \"Bio can not be empty\"\n        ],\n        \"name\": [\n            \"Name can not be empty\"\n        ]\n    },\n    \"message\": \"Validation error\"\n}"
						},
						{
							"name": "Empty request body",
							"originalRequest": {
								"method": "PUT",
								"header": [],
								"body": {
									"mode": "raw",
									"raw": "",
									"options": {
										"raw": {
											"language": "json"
										}
									}
								},
								"url": {
									"raw": "{{blog-server}}/v1/users/{{id}}",
									"host": [
										"{{blog-server}}"
									],
									"path": [
										"v1",
										"users",
										"{{id}}"
									]
								}
							},
							"status": "Bad Request",
							"code": 400,
							"_postman_previewlanguage": "json",
							"header": [
								{
									"key": "Content-Type",
									"value": "application/json; charset=utf-8"
								},
								{
									"key": "Date",
									"value": "Sun, 10 May 2020 18:55:25 GMT"
								},
								{
									"key": "Content-Length",
									"value": "34"
								}
							],
							"cookie": [],
							"body": "{\n    \"message\": \"Invalid request body\"\n}"
						},
						{
							"name": "Invalid username/password",
							"originalRequest": {
								"method": "POST",
								"header": [],
								"url": {
									"raw": "{{blog-server}}/users",
									"host": [
										"{{blog-server}}"
									],
									"path": [
										"users"
									]
								}
							},
							"status": "Unauthorized",
							"code": 401,
							"_postman_previewlanguage": "json",
							"header": [
								{
									"key": "Content-Type",
									"value": "application/json; charset=utf-8"
								},
								{
									"key": "Date",
									"value": "Sun, 10 May 2020 17:46:00 GMT"
								},
								{
									"key": "Content-Length",
									"value": "34"
								}
							],
							"cookie": [],
							"body": "{\n    \"message\": \"Unauthorized attempt\"\n}"
						},
						{
							"name": "Invalid user id",
							"originalRequest": {
								"method": "PUT",
								"header": [],
								"body": {
									"mode": "raw",
									"raw": "{\n\t\"name\": \"Captain Jack Sparrow\",\n\t\"bio\": \"Captain Jack Sparrow is a fictional character and the main protagonist of the Pirates of the Caribbean film series. The character was created by screenwriters Ted Elliott and Terry Rossio and is portrayed by Johnny Depp\"\n}",
									"options": {
										"raw": {
											"language": "json"
										}
									}
								},
								"url": {
									"raw": "{{blog-server}}/v1/users/{{invalid-id}}",
									"host": [
										"{{blog-server}}"
									],
									"path": [
										"v1",
										"users",
										"{{invalid-id}}"
									]
								}
							},
							"status": "Bad Request",
							"code": 400,
							"_postman_previewlanguage": "json",
							"header": [
								{
									"key": "Content-Type",
									"value": "application/json; charset=utf-8"
								},
								{
									"key": "Date",
									"value": "Sun, 10 May 2020 18:54:39 GMT"
								},
								{
									"key": "Content-Length",
									"value": "29"
								}
							],
							"cookie": [],
							"body": "{\n    \"message\": \"Invalid user id\"\n}"
						}
					]
				},
				{
					"name": "Delete user",
					"request": {
						"auth": {
							"type": "basic",
							"basic": [
								{
									"key": "password",
									"value": "password",
									"type": "string"
								},
								{
									"key": "username",
									"value": "username",
									"type": "string"
								},
								{
									"key": "saveHelperData",
									"type": "any"
								},
								{
									"key": "showPassword",
									"value": false,
									"type": "boolean"
								}
							]
						},
						"method": "DELETE",
						"header": [],
						"url": {
							"raw": "{{blog-server}}/v1/users/{{id}}",
							"host": [
								"{{blog-server}}"
							],
							"path": [
								"v1",
								"users",
								"{{id}}"
							]
						},
						"description": "Delete a single user using `id`"
					},
					"response": [
						{
							"name": "Success",
							"originalRequest": {
								"method": "DELETE",
								"header": [],
								"url": {
									"raw": "{{blog-server}}/v1/users/{{id}}",
									"host": [
										"{{blog-server}}"
									],
									"path": [
										"v1",
										"users",
										"{{id}}"
									]
								}
							},
							"status": "OK",
							"code": 200,
							"_postman_previewlanguage": "json",
							"header": [
								{
									"key": "Content-Type",
									"value": "application/json; charset=utf-8"
								},
								{
									"key": "Date",
									"value": "Sun, 10 May 2020 18:59:02 GMT"
								},
								{
									"key": "Content-Length",
									"value": "39"
								}
							],
							"cookie": [],
							"body": "{\n    \"message\": \"User deleted successfully\"\n}"
						},
						{
							"name": "Invalid user id",
							"originalRequest": {
								"method": "GET",
								"header": [],
								"url": {
									"raw": "{{blog-server}}/v1/users/{{invalid-id}}",
									"host": [
										"{{blog-server}}"
									],
									"path": [
										"v1",
										"users",
										"{{invalid-id}}"
									]
								}
							},
							"status": "Bad Request",
							"code": 400,
							"_postman_previewlanguage": "json",
							"header": [
								{
									"key": "Content-Type",
									"value": "application/json; charset=utf-8"
								},
								{
									"key": "Date",
									"value": "Sun, 10 May 2020 18:49:16 GMT"
								},
								{
									"key": "Content-Length",
									"value": "29"
								}
							],
							"cookie": [],
							"body": "{\n    \"message\": \"Invalid user id\"\n}"
						},
						{
							"name": "Invalid username/password",
							"originalRequest": {
								"method": "POST",
								"header": [],
								"url": {
									"raw": "{{blog-server}}/users",
									"host": [
										"{{blog-server}}"
									],
									"path": [
										"users"
									]
								}
							},
							"status": "Unauthorized",
							"code": 401,
							"_postman_previewlanguage": "json",
							"header": [
								{
									"key": "Content-Type",
									"value": "application/json; charset=utf-8"
								},
								{
									"key": "Date",
									"value": "Sun, 10 May 2020 17:46:00 GMT"
								},
								{
									"key": "Content-Length",
									"value": "34"
								}
							],
							"cookie": [],
							"body": "{\n    \"message\": \"Unauthorized attempt\"\n}"
						}
					]
				}
			],
			"description": "`Users` directory contains all the user related APIs. For authentication these apis requrie `BasicAuth`",
			"auth": {
				"type": "basic",
				"basic": [
					{
						"key": "password",
						"value": "password",
						"type": "string"
					},
					{
						"key": "username",
						"value": "username",
						"type": "string"
					},
					{
						"key": "saveHelperData",
						"type": "any"
					},
					{
						"key": "showPassword",
						"value": false,
						"type": "boolean"
					}
				]
			},
			"event": [
				{
					"listen": "prerequest",
					"script": {
						"id": "e06a7b80-9cdd-40da-bdda-9e4f23ad34f1",
						"type": "text/javascript",
						"exec": [
							""
						]
					}
				},
				{
					"listen": "test",
					"script": {
						"id": "31e3dfaa-4562-4bce-8f79-7f323d0ee7bf",
						"type": "text/javascript",
						"exec": [
							""
						]
					}
				}
			],
			"protocolProfileBehavior": {}
		},
		{
			"name": "Articles",
			"item": [
				{
					"name": "List articles",
					"request": {
						"auth": {
							"type": "bearer",
							"bearer": [
								{
									"key": "token",
									"value": "eyJhbGciOiJIUzI1NiIsInR5cCI6IkpXVCJ9.eyJzdWIiOiIxMjM0NTY3ODkwIiwibmFtZSI6IkpvaG4gRG9lIiwiaWF0IjoxNTE2MjM5MDIyfQ.SflKxwRJSMeKKF2QT4fwpMeJf36POk6yJV_adQssw5c",
									"type": "string"
								}
							]
						},
						"method": "GET",
						"header": [],
						"url": {
							"raw": "{{blog-server}}/v1/articles?page={{id}}&limit={{limit}}",
							"host": [
								"{{blog-server}}"
							],
							"path": [
								"v1",
								"articles"
							],
							"query": [
								{
									"key": "page",
									"value": "{{id}}",
									"description": "Page is a `unsigned integer` which represents the page numer"
								},
								{
									"key": "limit",
									"value": "{{limit}}",
									"description": "Limit represents maximum numer of results in the response"
								},
								{
									"key": "user_id",
									"value": "{{user_id}}",
									"description": "Filter the articles using *author_id*",
									"disabled": true
								}
							]
						},
						"description": "List articles endpoint provide article listing with *filtering*, *patination*"
					},
					"response": [
						{
							"name": "Invalid token",
							"originalRequest": {
								"method": "GET",
								"header": [],
								"url": {
									"raw": "{{blog-server}}/v1/articles?page={{id}}&limit={{limit}}&user_id={{user_id}}",
									"host": [
										"{{blog-server}}"
									],
									"path": [
										"v1",
										"articles"
									],
									"query": [
										{
											"key": "page",
											"value": "{{id}}",
											"description": "Page is a `unsigned integer` which represents the page numer"
										},
										{
											"key": "limit",
											"value": "{{limit}}",
											"description": "Limit represents maximum numer of results in the response"
										},
										{
											"key": "user_id",
											"value": "{{user_id}}",
											"description": "Filter the articles using *author_id*"
										}
									]
								}
							},
							"status": "Unauthorized",
							"code": 401,
							"_postman_previewlanguage": "json",
							"header": [
								{
									"key": "Content-Type",
									"value": "application/json; charset=utf-8"
								},
								{
									"key": "Date",
									"value": "Sun, 10 May 2020 19:14:51 GMT"
								},
								{
									"key": "Content-Length",
									"value": "32"
								}
							],
							"cookie": [],
							"body": "{\n    \"message\": \"Unauthorized token\"\n}"
						},
						{
							"name": "Success",
							"originalRequest": {
								"method": "GET",
								"header": [],
								"url": {
									"raw": "{{blog-server}}/v1/articles?page={{id}}&limit={{limit}}&user_id={{user_id}}",
									"host": [
										"{{blog-server}}"
									],
									"path": [
										"v1",
										"articles"
									],
									"query": [
										{
											"key": "page",
											"value": "{{id}}",
											"description": "Page is a `unsigned integer` which represents the page numer"
										},
										{
											"key": "limit",
											"value": "{{limit}}",
											"description": "Limit represents maximum numer of results in the response"
										},
										{
											"key": "user_id",
											"value": "{{user_id}}",
											"description": "Filter the articles using *author_id*"
										}
									]
								}
							},
							"status": "OK",
							"code": 200,
							"_postman_previewlanguage": "json",
							"header": [
								{
									"key": "Content-Type",
									"value": "application/json; charset=utf-8"
								},
								{
									"key": "Date",
									"value": "Sun, 10 May 2020 19:15:50 GMT"
								},
								{
									"key": "Content-Length",
									"value": "226"
								}
							],
							"cookie": [],
							"body": "{\n    \"data\": [\n        {\n            \"id\": 3,\n            \"user_id\": 10,\n            \"title\": \"Article 13\",\n            \"body\": \"This is article three\"\n        },\n        {\n            \"id\": 2,\n            \"user_id\": 10,\n            \"title\": \"Article 2\",\n            \"body\": \"This is article two\"\n        },\n        {\n            \"id\": 1,\n            \"user_id\": 10,\n            \"title\": \"Article 1\",\n            \"body\": \"This is article one\"\n        }\n    ]\n}"
						},
						{
							"name": "Without filtering",
							"originalRequest": {
								"method": "GET",
								"header": [],
								"url": {
									"raw": "{{blog-server}}/v1/articles?page={{id}}&limit={{limit}}",
									"host": [
										"{{blog-server}}"
									],
									"path": [
										"v1",
										"articles"
									],
									"query": [
										{
											"key": "page",
											"value": "{{id}}",
											"description": "Page is a `unsigned integer` which represents the page numer"
										},
										{
											"key": "limit",
											"value": "{{limit}}",
											"description": "Limit represents maximum numer of results in the response"
										},
										{
											"key": "user_id",
											"value": "{{user_id}}",
											"description": "Filter the articles using *author_id*",
											"disabled": true
										}
									]
								}
							},
							"status": "OK",
							"code": 200,
							"_postman_previewlanguage": "json",
							"header": null,
							"cookie": [],
							"body": "{\n    \"data\": [\n        {\n            \"id\": 3,\n            \"user_id\": 10,\n            \"title\": \"Article 13\",\n            \"body\": \"This is article three\"\n        },\n        {\n            \"id\": 2,\n            \"user_id\": 10,\n            \"title\": \"Article 2\",\n            \"body\": \"This is article two\"\n        },\n        {\n            \"id\": 1,\n            \"user_id\": 10,\n            \"title\": \"Article 1\",\n            \"body\": \"This is article one\"\n        }\n    ]\n}"
						}
					]
				}
			],
			"description": "`Articles` directory contains all the article related APIs. Use `JWT` toekn for authentications for articles API.",
			"auth": {
				"type": "bearer",
				"bearer": [
					{
						"key": "token",
						"value": "eyJhbGciOiJIUzI1NiIsInR5cCI6IkpXVCJ9.eyJzdWIiOiIxMjM0NTY3ODkwIiwibmFtZSI6IkpvaG4gRG9lIiwiaWF0IjoxNTE2MjM5MDIyfQ.SflKxwRJSMeKKF2QT4fwpMeJf36POk6yJV_adQssw5c",
						"type": "string"
					}
				]
			},
			"event": [
				{
					"listen": "prerequest",
					"script": {
						"id": "368bf88a-3db6-41aa-85c9-5daecd705532",
						"type": "text/javascript",
						"exec": [
							""
						]
					}
				},
				{
					"listen": "test",
					"script": {
						"id": "14adfa0c-c5ae-4931-b2a5-779b6eee4467",
						"type": "text/javascript",
						"exec": [
							""
						]
					}
				}
			],
			"protocolProfileBehavior": {}
		},
		{
			"name": "Health check",
			"request": {
				"method": "GET",
				"header": [],
				"url": {
					"raw": "{{blog-server}}/",
					"host": [
						"{{blog-server}}"
					],
					"path": [
						""
					]
				},
				"description": "System health check endpoint provide system health status for `probe`"
			},
			"response": [
				{
					"name": "Error",
					"originalRequest": {
						"method": "GET",
						"header": [],
						"url": {
							"raw": "{{blog-server}}/",
							"host": [
								"{{blog-server}}"
							],
							"path": [
								""
							]
						}
					},
					"status": "Internal Server Error",
					"code": 500,
					"_postman_previewlanguage": "json",
					"header": [
						{
							"key": "Content-Type",
							"value": "application/json; charset=utf-8"
						},
						{
							"key": "Date",
							"value": "Sun, 10 May 2020 19:02:53 GMT"
						},
						{
							"key": "Content-Length",
							"value": "19"
						}
					],
					"cookie": [],
					"body": "{\n    \"system\": \"Failed\"\n}"
				},
				{
					"name": "Success",
					"originalRequest": {
						"method": "GET",
						"header": [],
						"url": {
							"raw": "{{blog-server}}/",
							"host": [
								"{{blog-server}}"
							],
							"path": [
								""
							]
						}
					},
					"status": "OK",
					"code": 200,
					"_postman_previewlanguage": "json",
					"header": [
						{
							"key": "Content-Type",
							"value": "application/json; charset=utf-8"
						},
						{
							"key": "Date",
							"value": "Sun, 10 May 2020 19:02:27 GMT"
						},
						{
							"key": "Content-Length",
							"value": "15"
						}
					],
					"cookie": [],
					"body": "{\n    \"system\": \"OK\"\n}"
				}
			]
		}
	],
	"protocolProfileBehavior": {}
}